snmp_manager/__init__.py
snmp_manager/adaptive/__init__.py
snmp_manager/adaptive/adapter_generator.py
snmp_manager/adaptive/fallback_strategies.py
snmp_manager/adaptive/self_learning.py
snmp_manager/collectors/olt_collector.py
snmp_manager/config/__init__.py
snmp_manager/config/adapter.py
snmp_manager/config/manager.py
snmp_manager/core/__init__.py
snmp_manager/core/device.py
snmp_manager/core/engine.py
snmp_manager/core/enhanced_device.py
snmp_manager/core/manager.py
snmp_manager/discovery/__init__.py
snmp_manager/discovery/fingerprinter.py
snmp_manager/discovery/prober.py
snmp_manager/discovery/scanner.py
snmp_manager/intelligence/__init__.py
snmp_manager/intelligence/knowledge_base.py
snmp_manager/intelligence/oid_explorer.py
snmp_manager/intelligence/pattern_recognition.py
snmp_manager/intelligence/reverse_engineer.py
snmp_manager/scheduler/task_scheduler.py
snmp_manager/storage/database_converter.py
snmp_manager/utils/data_structures.py
snmp_manager/validation/data_validator.py
snmpbox-0.1.1.dist-info/licenses/LICENSE
snmpbox-0.1.1.dist-info/METADATA
snmpbox-0.1.1.dist-info/WHEEL
snmpbox-0.1.1.dist-info/entry_points.txt
snmpbox-0.1.1.dist-info/top_level.txt
snmpbox-0.1.1.dist-info/RECORD
