Metadata-Version: 2.4
Name: snmpbox
Version: 0.1.1
Summary: Intelligent SNMP data collection system for telecom devices with automatic discovery and reverse engineering
Home-page: https://github.com/mexyusef/snmp-manager
Author: Yusef Ulum
Author-email: Yusef Ulum <yusef314159@gmail.com>
Maintainer: Yusef Ulum
Maintainer-email: Yusef Ulum <yusef314159@gmail.com>
License-Expression: MIT
Project-URL: Homepage, https://github.com/mexyusef/snmp-manager
Project-URL: Documentation, https://snmp-manager.readthedocs.io/
Project-URL: Repository, https://github.com/mexyusef/snmp-manager.git
Project-URL: Bug Reports, https://github.com/mexyusef/snmp-manager/issues
Project-URL: Discussions, https://github.com/mexyusef/snmp-manager/discussions
Project-URL: Changelog, https://github.com/mexyusef/snmp-manager/blob/main/CHANGELOG.md
Keywords: snmp,telecom,network-monitoring,olt,onu,gpon,device-discovery,reverse-engineering,intelligence,automation,huawei,zte,vsol
Classifier: Development Status :: 4 - Beta
Classifier: Intended Audience :: Developers
Classifier: Intended Audience :: System Administrators
Classifier: Intended Audience :: Telecommunications Industry
Classifier: Operating System :: OS Independent
Classifier: Programming Language :: Python :: 3
Classifier: Programming Language :: Python :: 3.8
Classifier: Programming Language :: Python :: 3.9
Classifier: Programming Language :: Python :: 3.10
Classifier: Programming Language :: Python :: 3.11
Classifier: Programming Language :: Python :: 3.12
Classifier: Topic :: System :: Networking
Classifier: Topic :: System :: Monitoring
Classifier: Topic :: System :: Hardware :: Hardware Drivers
Classifier: Topic :: Software Development :: Libraries :: Python Modules
Classifier: Topic :: Communications
Classifier: Environment :: Console
Requires-Python: >=3.8
License-File: LICENSE
Requires-Dist: pysnmp>=7.1.0
Requires-Dist: pyyaml>=6.0
Requires-Dist: asyncio-throttle>=1.0.0
Requires-Dist: aiofiles>=0.8.0
Requires-Dist: netaddr>=0.8.0
Requires-Dist: pydantic>=1.10.0
Requires-Dist: click>=8.0.0
Requires-Dist: rich>=12.0.0
Requires-Dist: typing-extensions>=4.0.0
Provides-Extra: dev
Requires-Dist: pytest>=7.0.0; extra == "dev"
Requires-Dist: pytest-asyncio>=0.20.0; extra == "dev"
Requires-Dist: pytest-cov>=4.0.0; extra == "dev"
Requires-Dist: black>=22.0.0; extra == "dev"
Requires-Dist: isort>=5.10.0; extra == "dev"
Requires-Dist: mypy>=0.991; extra == "dev"
Requires-Dist: pre-commit>=2.20.0; extra == "dev"
Requires-Dist: flake8>=4.0.0; extra == "dev"
Requires-Dist: twine>=4.0.0; extra == "dev"
Requires-Dist: wheel>=0.40.0; extra == "dev"
Requires-Dist: build>=0.8.0; extra == "dev"
Provides-Extra: ml
Requires-Dist: scikit-learn>=1.1.0; extra == "ml"
Requires-Dist: numpy>=1.21.0; extra == "ml"
Requires-Dist: pandas>=1.4.0; extra == "ml"
Requires-Dist: scipy>=1.9.0; extra == "ml"
Provides-Extra: docs
Requires-Dist: sphinx>=7.0.0; extra == "docs"
Requires-Dist: sphinx-rtd-theme>=2.0.0; extra == "docs"
Requires-Dist: sphinx-autobuild>=2021.3.14; extra == "docs"
Provides-Extra: visualization
Requires-Dist: matplotlib>=3.5.0; extra == "visualization"
Requires-Dist: seaborn>=0.11.0; extra == "visualization"
Requires-Dist: plotly>=5.0.0; extra == "visualization"
Provides-Extra: enterprise
Requires-Dist: celery>=5.2.0; extra == "enterprise"
Requires-Dist: redis>=4.3.0; extra == "enterprise"
Requires-Dist: psycopg2-binary>=2.9.0; extra == "enterprise"
Requires-Dist: sqlalchemy>=1.4.0; extra == "enterprise"
Dynamic: author
Dynamic: home-page
Dynamic: license-file
Dynamic: maintainer
Dynamic: requires-python
